carica_dynamodb_tools/__init__.py
carica_dynamodb_tools/dump.py
carica_dynamodb_tools/dump_s3_export.py
carica_dynamodb_tools/load.py
carica_dynamodb_tools/s3_export.py
carica_dynamodb_tools/session.py
carica_dynamodb_tools/utils.py
carica_dynamodb_tools/version.py
carica_dynamodb_tools-1.8.dist-info/LICENSE
carica_dynamodb_tools-1.8.dist-info/METADATA
carica_dynamodb_tools-1.8.dist-info/WHEEL
carica_dynamodb_tools-1.8.dist-info/entry_points.txt
carica_dynamodb_tools-1.8.dist-info/top_level.txt
carica_dynamodb_tools-1.8.dist-info/RECORD
