Metadata-Version: 2.1
Name: carica-dynamodb-tools
Version: 1.8
Summary: Tools to manage DynamoDB tables
Home-page: https://github.com/caricalabs/carica-dynamodb-tools
Author: Carica Labs, LLC
Author-email: info@caricalabs.com
License: APL 2.0
Keywords: dynamodb backup restore archive dump load
Platform: UNKNOWN
Classifier: Development Status :: 5 - Production/Stable
Classifier: Intended Audience :: System Administrators
Classifier: License :: OSI Approved :: Apache Software License
Classifier: Programming Language :: Python :: 3.7
Requires-Dist: boto3 (>=1.9.99)
Requires-Dist: click (~=8.0)
Requires-Dist: orjson (~=3.9.2)
Provides-Extra: dev
Requires-Dist: check-manifest ; extra == 'dev'
Provides-Extra: test
